pvutil/.version
pvutil/__init__.py
pvutil/cmd.py
pvutil-0.0.7.dist-info/METADATA
pvutil-0.0.7.dist-info/RECORD
pvutil-0.0.7.dist-info/WHEEL
pvutil-0.0.7.dist-info/top_level.txt
