Metadata-Version: 2.1
Name: pvutil
Version: 0.0.7
Summary: pyviz user utilities (e.g. install examples, download data, ...
Home-page: http://github.com/pyviz/pyct
License: BSD-3
Platform: UNKNOWN
Requires-Python: >=2.7
Provides-Extra: tests
Requires-Dist: pyyaml
Requires-Dist: requests
Provides-Extra: tests
Requires-Dist: flake8; extra == 'tests'
